wltr_ebct_finder/__init__.py
wltr_ebct_finder/ebct_api.py
wltr_ebct_finder-1.1.0.dist-info/LICENSE
wltr_ebct_finder-1.1.0.dist-info/METADATA
wltr_ebct_finder-1.1.0.dist-info/WHEEL
wltr_ebct_finder-1.1.0.dist-info/top_level.txt
wltr_ebct_finder-1.1.0.dist-info/RECORD
