Metadata-Version: 2.1
Name: wltr-ebct-finder
Version: 1.1.0
Summary: API para consulta de endereço e CEP
Home-page: https://github.com/walteravelino/wltr-ebct-finder
Author: Walter Avelino
Author-email: walter.avelin@gmail.com
License: UNKNOWN
Keywords: cep endereco correios ebct api busca
Platform: UNKNOWN
Classifier: Programming Language :: Python :: 3
Classifier: License :: OSI Approved :: MIT License
Classifier: Operating System :: OS Independent
Classifier: Natural Language :: Portuguese
Classifier: Intended Audience :: Developers
License-File: LICENSE
Requires-Dist: beautifulsoup4
Requires-Dist: requests
Requires-Dist: unidecode
